memory.v
module memory(
    input wire clk,
    input wire rst,
    input wire data_e,
    input wire wrt,
    input wire rd, 
    input wire is_zero,
    input wire [4:0] mux_addr,
    inout wire [7:0] data_bus,
    output reg [7:0] mem_out
);

reg [7:0] memory[0:31];

integer i;
initial begin
    for (i = 0; i < 32; i = i + 1) begin
        memory[i] = 8'b0;
    end
    $readmemb("memory_init.bin", memory);
end

assign data_bus = (data_e && wrt) ? mem_out : 8'bz;

always @(posedge clk or posedge rst) begin
    if (rst) begin
        mem_out <= 8'b0;
    end
    else begin
        if (rd) begin
            mem_out <= memory[mux_addr];
        end
        else if (wrt && data_e) begin
            memory[mux_addr] <= data_bus;
            mem_out <= data_bus;
        end
    end
end

endmodule

address_mux.v
module address_mux(
    input wire sel,
    input wire [4:0] pc,
    input wire [4:0] address,
    output wire [4:0] mux_addr
);

assign mux_addr = sel ? pc : address;

endmodule

alu.v
module alu(
    input wire [2:0] opcode,
    input wire [7:0] acc_data,
    input wire [7:0] mem_out,
    output reg [7:0] result,
    output reg is_zero
);

always @(*) begin
    case (opcode)
        3'b010: result = acc_data + mem_out;  // ADD
        3'b011: result = acc_data & mem_out;  // AND
        3'b100: result = acc_data ^ mem_out;  // XOR
        3'b101: result = mem_out;             // LDA
        default: result = acc_data;           // Default case
    endcase
    
    is_zero = (result == 8'b0);
end

endmodule

acc.v
module acc(
    input wire clk,
    input wire rst,
    input wire ld_ac,
    input wire [7:0] result,
    output reg [7:0] acc_data
);

always @(posedge clk or posedge rst) begin
    if (rst)
        acc_data <= 8'b0;
    else if (ld_ac)
        acc_data <= result;
end

endmodule

ir.v
module ir(
    input wire clk, 
    input wire rst,
    input wire ld_ir,
    input wire [7:0] mem_out,
    output reg [2:0] opcode,
    output reg [4:0] address
);

always @(posedge clk or posedge rst) begin
    if (rst) begin
        opcode <= 3'b0;
        address <= 5'b0;
    end
    else if (ld_ir) begin
        opcode <= mem_out[7:5];
        address <= mem_out[4:0];
    end
end

endmodule

pc.v
module pc(
    input wire clk,
    input wire rst, 
    input wire ld_pc,
    input wire inc_pc,
    input wire [4:0] mux_addr,

    output reg [4:0] pc
);

always @(posedge clk or posedge rst) begin
    if (rst) 
        pc <= 5'b0; 
    else if (ld_pc) 
        pc <= mux_addr;
    else if(inc_pc) begin
        pc <= pc + 1;
    end 
    else 
        pc <= pc; 
end

endmodule

controller.v
module controller(
    input wire clk,
    input wire rst,
    input wire [2:0] opcode,
    output reg sel,
    output reg rd,
    output reg ld_ir,
    output reg halt,
    output reg inc_pc,
    output reg ld_ac,
    output reg ld_pc,
    output reg wr,
    output reg data_e
);

parameter INST_ADDR  = 3'd0;
parameter INST_FETCH = 3'd1;
parameter INST_LOAD  = 3'd2;
parameter IDLE       = 3'd3; 
parameter OP_ADDR    = 3'd4;
parameter OP_FETCH   = 3'd5;
parameter ALU_OP     = 3'd6;
parameter STORE      = 3'd7;

parameter HLT = 3'b000;
parameter SKZ = 3'b001;
parameter ADD = 3'b010;
parameter AND = 3'b011;
parameter XOR = 3'b100;
parameter LDA = 3'b101;
parameter STO = 3'b110;
parameter JMP = 3'b111;

reg [2:0] state;

always @(posedge clk or posedge rst) begin
    if (rst) begin
        state <= INST_ADDR;
        sel <= 1'b0;
        rd <= 1'b0;
        ld_ir <= 1'b0;
        halt <= 1'b0;
        inc_pc <= 1'b0;
        ld_ac <= 1'b0;
        ld_pc <= 1'b0;
        wr <= 1'b0;
        data_e <= 1'b0;
    end
    else begin
        case (state)
            INST_ADDR: begin
                sel     <= 1'b1;
                rd      <= 1'b0;
                ld_ir   <= 1'b0;
                halt    <= 1'b0;
                inc_pc  <= 1'b0;
                ld_ac   <= 1'b0;
                ld_pc   <= 1'b0;
                wr      <= 1'b0;
                data_e  <= 1'b0;
                state   <= INST_FETCH;
            end

            INST_FETCH: begin
                sel     <= 1'b1;
                rd      <= 1'b1;
                ld_ir   <= 1'b0;
                halt    <= 1'b0;
                inc_pc  <= 1'b0;
                ld_ac   <= 1'b0;
                ld_pc   <= 1'b0;
                wr      <= 1'b0;
                data_e  <= 1'b0;
                state   <= INST_LOAD;
            end

            INST_LOAD: begin
                sel     <= 1'b1;
                rd      <= 1'b1;
                ld_ir   <= 1'b1;
                halt    <= 1'b0;
                inc_pc  <= 1'b0;
                ld_ac   <= 1'b0;
                ld_pc   <= 1'b0;
                wr      <= 1'b0;
                data_e  <= 1'b0;
                state   <= IDLE;
            end
            
            IDLE: begin
                sel     <= 1'b1;
                rd      <= 1'b1;
                ld_ir   <= 1'b1;
                halt    <= 1'b0;
                inc_pc  <= 1'b0;
                ld_ac   <= 1'b0;
                ld_pc   <= 1'b0;
                wr      <= 1'b0;
                data_e  <= 1'b0;
                state   <= OP_ADDR;
            end

            OP_ADDR: begin
                sel     <= 1'b0;
                rd      <= 1'b0;
                ld_ir   <= 1'b0;
                halt    <= (opcode == HLT) ? 1'b1 : 1'b0;
                inc_pc  <= 1'b1;
                ld_ac   <= 1'b0;
                ld_pc   <= 1'b0;
                wr      <= 1'b0;
                data_e  <= 1'b0;
                if (opcode == HLT) begin
                    state <= OP_ADDR;
                end
                else
                    state <= OP_FETCH;
            end

            OP_FETCH: begin
                sel     <= 1'b0;
                rd      <= (opcode == ADD || opcode == AND || opcode == XOR || opcode == LDA) ? 1'b1 : 1'b0;
                ld_ir   <= 1'b0;
                halt    <= 1'b0;
                inc_pc  <= 1'b0;
                ld_ac   <= 1'b0;
                ld_pc   <= 1'b0;
                wr      <= 1'b0;
                data_e  <= 1'b0;
                state   <= ALU_OP;
            end

            ALU_OP: begin
                sel     <= 1'b0;
                rd      <= (opcode == ADD || opcode == AND || opcode == XOR || opcode == LDA) ? 1'b1 : 1'b0;
                ld_ir   <= 1'b0;
                halt    <= 1'b0;
                inc_pc  <= (opcode == SKZ && is_zero) ;
                ld_ac   <= 1'b0;
                ld_pc   <= (opcode == JMP) ? 1'b1 : 1'b0;
                wr      <= 1'b0;
                data_e  <= (opcode == STO) ? 1'b1 : 1'b0;
                state   <= STORE;
            end

            STORE: begin
                sel     <= 1'b0;
                rd      <= (opcode == ADD || opcode == AND || opcode == XOR || opcode == LDA) ? 1'b1 : 1'b0;
                ld_ir   <= 1'b0;
                halt    <= 1'b0;
                inc_pc  <= 1'b0;
                ld_ac   <= (opcode == ADD || opcode == AND || opcode == XOR || opcode == LDA) ? 1'b1 : 1'b0;
                ld_pc   <= (opcode == JMP) ? 1'b1 : 1'b0;
                wr      <= (opcode == STO) ? 1'b1 : 1'b0;
                data_e  <= (opcode == STO) ? 1'b1 : 1'b0;
                state   <= INST_ADDR;
            end

            default: begin
                sel     <= 1'b0;
                rd      <= 1'b0;
                ld_ir   <= 1'b0;
                halt    <= 1'b0;
                inc_pc  <= 1'b0;
                ld_ac   <= 1'b0;
                ld_pc   <= 1'b0;
                wr      <= 1'b0;
                data_e  <= 1'b0;
                state   <= INST_ADDR;
            end
        endcase
    end
end
endmodule

cpu.v
`include "controller.v"
`include "pc.v"
`include "ir.v"
`include "acc.v"
`include "alu.v"
`include "address_mux.v"
`include "memory.v"

module cpu(
    input wire clk,
    input wire rst,
    output wire halt_out
);

    wire [2:0] opcode;
    wire [7:0] mem_out;
    wire [4:0] address;
    wire [7:0] result;
    wire [7:0] acc_data;
    wire [4:0] pc;
    wire [4:0] mux_addr;
    wire [7:0] data_bus;

    wire sel, rd, ld_ir, inc_pc, ld_ac, ld_pc, wr, data_e, is_zero;

    controller ctrl(
        .clk(clk),
        .rst(rst),
        .opcode(opcode),
        .is_zero(is_zero),
        .sel(sel),
        .rd(rd),
        .ld_ir(ld_ir),
        .halt(halt_out),
        .inc_pc(inc_pc),
        .ld_ac(ld_ac),
        .ld_pc(ld_pc),
        .wr(wr),
        .data_e(data_e)
    );

    pc program_counter(
        .clk(clk),
        .rst(rst),
        .ld_pc(ld_pc),
        .inc_pc(inc_pc),
        .mux_addr(mux_addr),
        .pc(pc)
    );

    ir instruction_register(
        .clk(clk),
        .rst(rst),
        .ld_ir(ld_ir),
        .mem_out(mem_out),
        .opcode(opcode),
        .address(address)
    );

    acc accumulator(
        .clk(clk),
        .rst(rst),
        .ld_ac(ld_ac),
        .result(result),
        .acc_data(acc_data)
    );

    alu u_alu(
        .opcode(opcode),
        .acc_data(acc_data),
        .mem_out(mem_out),
        .result(result),
        .is_zero(is_zero)
    );

    address_mux addr_mux(
        .sel(sel),
        .pc(pc),
        .address(address),
        .mux_addr(mux_addr)
    );

    memory mem(
        .clk(clk),
        .rst(rst),
        .data_e(data_e),
        .wrt(wr),
        .rd(rd),
        .mux_addr(mux_addr),
        .data_bus(data_bus),
        .mem_out(mem_out)
    );

    // Kết nối bus dữ liệu
    assign data_bus = (data_e && wr) ? acc_data : 8'bz;
endmodule

test_bench.v
`include "cpu.v"
module tb_cpu;
reg clk;
reg rst;

cpu u_cpu(
    .clk(clk),
    .rst(rst)
);

localparam CLK_PERIOD = 10;
always #(CLK_PERIOD/2) clk=~clk;

initial begin
    $dumpfile("tb_cpu.vcd");
    $dumpvars(0, tb_cpu);
end

initial begin
    clk = 1'b1 ;
    rst = 1'b1 ; #10
    rst = 1'b0 ; 
    #2000 $finish;
end

endmodule

tb_cpu.vcd
$date
	Thu May 29 13:55:15 2025
$end
$version
	Icarus Verilog
$end
$timescale
	1s
$end
$scope module tb_cpu $end
$var parameter 32 ! CLK_PERIOD $end
$var reg 1 " clk $end
$var reg 1 # rst $end
$scope module u_cpu $end
$var wire 1 " clk $end
$var wire 8 $ data_bus [7:0] $end
$var wire 1 # rst $end
$var wire 1 % wr $end
$var wire 1 & sel $end
$var wire 8 ' result [7:0] $end
$var wire 1 ( rd $end
$var wire 5 ) pc [4:0] $end
$var wire 3 * opcode [2:0] $end
$var wire 5 + mux_addr [4:0] $end
$var wire 8 , mem_out [7:0] $end
$var wire 1 - ld_pc $end
$var wire 1 . ld_ir $end
$var wire 1 / ld_ac $end
$var wire 1 0 is_zero $end
$var wire 1 1 inc_pc $end
$var wire 1 2 halt_out $end
$var wire 1 3 data_e $end
$var wire 5 4 address [4:0] $end
$var wire 8 5 acc_data [7:0] $end
$scope module accumulator $end
$var wire 1 " clk $end
$var wire 1 # rst $end
$var wire 8 6 result [7:0] $end
$var wire 1 / ld_ac $end
$var reg 8 7 acc_data [7:0] $end
$upscope $end
$scope module addr_mux $end
$var wire 1 & sel $end
$var wire 5 8 pc [4:0] $end
$var wire 5 9 mux_addr [4:0] $end
$var wire 5 : address [4:0] $end
$upscope $end
$scope module ctrl $end
$var wire 1 " clk $end
$var wire 1 # rst $end
$var wire 3 ; opcode [2:0] $end
$var wire 1 0 is_zero $end
$var parameter 3 < ADD $end
$var parameter 3 = ALU_OP $end
$var parameter 3 > AND $end
$var parameter 3 ? HLT $end
$var parameter 3 @ IDLE $end
$var parameter 3 A INST_ADDR $end
$var parameter 3 B INST_FETCH $end
$var parameter 3 C INST_LOAD $end
$var parameter 3 D JMP $end
$var parameter 3 E LDA $end
$var parameter 3 F OP_ADDR $end
$var parameter 3 G OP_FETCH $end
$var parameter 3 H SKZ $end
$var parameter 3 I STO $end
$var parameter 3 J STORE $end
$var parameter 3 K XOR $end
$var reg 1 3 data_e $end
$var reg 1 2 halt $end
$var reg 1 1 inc_pc $end
$var reg 1 / ld_ac $end
$var reg 1 . ld_ir $end
$var reg 1 - ld_pc $end
$var reg 1 ( rd $end
$var reg 1 & sel $end
$var reg 3 L state [2:0] $end
$var reg 1 % wr $end
$upscope $end
$scope module instruction_register $end
$var wire 1 " clk $end
$var wire 1 . ld_ir $end
$var wire 1 # rst $end
$var wire 8 M mem_out [7:0] $end
$var reg 5 N address [4:0] $end
$var reg 3 O opcode [2:0] $end
$upscope $end
$scope module mem $end
$var wire 1 " clk $end
$var wire 8 P data_bus [7:0] $end
$var wire 1 3 data_e $end
$var wire 1 Q is_zero $end
$var wire 5 R mux_addr [4:0] $end
$var wire 1 ( rd $end
$var wire 1 # rst $end
$var wire 1 % wrt $end
$var reg 8 S mem_out [7:0] $end
$var integer 32 T i [31:0] $end
$upscope $end
$scope module program_counter $end
$var wire 1 " clk $end
$var wire 1 1 inc_pc $end
$var wire 1 - ld_pc $end
$var wire 5 U mux_addr [4:0] $end
$var wire 1 # rst $end
$var reg 5 V pc [4:0] $end
$upscope $end
$scope module u_alu $end
$var wire 8 W acc_data [7:0] $end
$var wire 8 X mem_out [7:0] $end
$var wire 3 Y opcode [2:0] $end
$var wire 8 Z result [7:0] $end
$var wire 1 0 is_zero $end
$upscope $end
$upscope $end
$upscope $end
$enddefinitions $end
$comment Show the parameter values. $end
$dumpall
b100 K
b111 J
b110 I
b1 H
b101 G
b100 F
b101 E
b111 D
b10 C
b1 B
b0 A
b11 @
b0 ?
b11 >
b110 =
b10 <
b1010 !
$end
#0
$dumpvars
b0 Z
b0 Y
b0 X
b0 W
b0 V
b0 U
b100000 T
b0 S
b0 R
zQ
bz P
b0 O
b0 N
b0 M
b0 L
b0 ;
b0 :
b0 9
b0 8
b0 7
b0 6
b0 5
b0 4
03
02
01
10
0/
0.
0-
b0 ,
b0 +
b0 *
b0 )
0(
b0 '
0&
0%
bz $
1#
1"
$end
#5
0"
#10
b1 L
1&
1"
0#
#15
0"
#20
b10 L
1(
1"
#25
0"
#30
b11111110 ,
b11111110 M
b11111110 S
b11111110 X
b11 L
1.
1"
#35
0"
#40
b100 L
b11110 4
b11110 :
b11110 N
b111 *
b111 ;
b111 O
b111 Y
1"
#45
0"
#50
b11110 +
b11110 9
b11110 R
b11110 U
b101 L
11
0.
0(
0&
1"
#55
0"
#60
b110 L
01
b1 )
b1 8
b1 V
1"
#65
0"
#70
b111 L
1-
1"
#75
0"
#80
b0 L
b11110 )
b11110 8
b11110 V
1"
#85
0"
#90
b1 L
0-
1&
1"
#95
0"
#100
b10 L
1(
1"
#105
0"
#110
b0 ,
b0 M
b0 S
b0 X
b11 L
1.
1"
#115
0"
#120
b100 L
b0 4
b0 :
b0 N
b0 *
b0 ;
b0 O
b0 Y
1"
#125
0"
#130
b0 +
b0 9
b0 R
b0 U
b101 L
12
0.
0(
0&
1"
#135
0"
#140
b110 L
02
1"
#145
0"
#150
b111 L
1"
#155
0"
#160
b0 L
1"
#165
0"
#170
b11110 +
b11110 9
b11110 R
b11110 U
b1 L
1&
1"
#175
0"
#180
b10 L
1(
1"
#185
0"
#190
b11 L
1.
1"
#195
0"
#200
b100 L
1"
#205
0"
#210
b0 +
b0 9
b0 R
b0 U
b101 L
12
0.
0(
0&
1"
#215
0"
#220
b110 L
02
1"
#225
0"
#230
b111 L
1"
#235
0"
#240
b0 L
1"
#245
0"
#250
b11110 +
b11110 9
b11110 R
b11110 U
b1 L
1&
1"
#255
0"
#260
b10 L
1(
1"
#265
0"
#270
b11 L
1.
1"
#275
0"
#280
b100 L
1"
#285
0"
#290
b0 +
b0 9
b0 R
b0 U
b101 L
12
0.
0(
0&
1"
#295
0"
#300
b110 L
02
1"
#305
0"
#310
b111 L
1"
#315
0"
#320
b0 L
1"
#325
0"
#330
b11110 +
b11110 9
b11110 R
b11110 U
b1 L
1&
1"
#335
0"
#340
b10 L
1(
1"
#345
0"
#350
b11 L
1.
1"
#355
0"
#360
b100 L
1"
#365
0"
#370
b0 +
b0 9
b0 R
b0 U
b101 L
12
0.
0(
0&
1"
#375
0"
#380
b110 L
02
1"
#385
0"
#390
b111 L
1"
#395
0"
#400
b0 L
1"
#405
0"
#410
b11110 +
b11110 9
b11110 R
b11110 U
b1 L
1&
1"
#415
0"
#420
b10 L
1(
1"
#425
0"
#430
b11 L
1.
1"
#435
0"
#440
b100 L
1"
#445
0"
#450
b0 +
b0 9
b0 R
b0 U
b101 L
12
0.
0(
0&
1"
#455
0"
#460
b110 L
02
1"
#465
0"
#470
b111 L
1"
#475
0"
#480
b0 L
1"
#485
0"
#490
b11110 +
b11110 9
b11110 R
b11110 U
b1 L
1&
1"
#495
0"
#500
b10 L
1(
1"
#505
0"
#510
b11 L
1.
1"
